melange/__init__.py
melange/__version__.py
melange/backends/__init__.py
melange/backends/backend_manager.py
melange/backends/factory.py
melange/backends/interfaces.py
melange/backends/kafka.py
melange/backends/rabbitmq/__init__.py
melange/backends/rabbitmq/rabbitmq_backend.py
melange/backends/sqs/__init__.py
melange/backends/sqs/localsqs.py
melange/backends/sqs/message_validator.py
melange/backends/sqs/sqs_backend.py
melange/backends/testing.py
melange/consumers.py
melange/examples/README.md
melange/examples/__init__.py
melange/examples/common/__init__.py
melange/examples/common/commands.py
melange/examples/common/domain.py
melange/examples/doc_examples/__init__.py
melange/examples/doc_examples/backend_manager.py
melange/examples/doc_examples/factory_complete.py
melange/examples/doc_examples/factory_queue.py
melange/examples/doc_examples/factory_topic.py
melange/examples/doc_examples/serializer_example.py
melange/examples/doc_examples/topic_publish.py
melange/examples/doc_examples/tutorial/__init__.py
melange/examples/doc_examples/tutorial/consume.py
melange/examples/doc_examples/tutorial/create_queue.py
melange/examples/doc_examples/tutorial/publish.py
melange/examples/init_queues.py
melange/examples/payment_service/__init__.py
melange/examples/payment_service/app.py
melange/examples/payment_service/app_simpleconsumer.py
melange/examples/payment_service/consumer.py
melange/examples/payment_service/consumer_draft.py
melange/examples/payment_service/events.py
melange/examples/payment_service/publisher.py
melange/examples/payment_service/repository.py
melange/examples/payment_service/service.py
melange/examples/payment_service/triggerer.py
melange/examples/saga_pattern/__init__.py
melange/examples/saga_pattern/app.py
melange/examples/saga_pattern/consumer.py
melange/examples/saga_pattern/models.py
melange/examples/saga_pattern/publisher.py
melange/examples/saga_pattern/repository.py
melange/examples/saga_pattern/saga_triggerer.py
melange/examples/shared.py
melange-7.2.0.dist-info/LICENSE
melange-7.2.0.dist-info/WHEEL
melange-7.2.0.dist-info/METADATA
melange-7.2.0.dist-info/RECORD
